hydroloader/__init__.py
hydroloader/exceptions.py
hydroloader/main.py
hydroloader/models.py
hydroloader-0.1.15.dist-info/LICENSE
hydroloader-0.1.15.dist-info/METADATA
hydroloader-0.1.15.dist-info/WHEEL
hydroloader-0.1.15.dist-info/top_level.txt
hydroloader-0.1.15.dist-info/zip-safe
hydroloader-0.1.15.dist-info/RECORD
