Metadata-Version: 2.1
Name: hydroloader
Version: 0.1.15
License-File: LICENSE
Requires-Dist: requests >=2
Requires-Dist: pydantic <2.0.0,>=1.6
Requires-Dist: pyyaml >=5
Requires-Dist: simplejson >=3
Requires-Dist: crontab >=1
Requires-Dist: python-dateutil >=2.8.2
Provides-Extra: docs
Requires-Dist: sphinx-autodoc-typehints ; extra == 'docs'
